{
  "title": "Lesson 1: List file",
  "description": "",
  "details": {
    "intro": {
      "text": "intro.md"
    },
    "steps": [
      {
        "title": "1. Cái nhìn đầu về lệnh ls",
        "text": "step1/text.md"
      },
      {
        "title": "2. Thêm thông tin chi tiết",
        "text": "step2/text.md"
      },
      {
        "title": "3. Liệt kê tất cả đối tượng",
        "text": "step3/text.md"
      }
    ],
    "finish": {
      "text": "finish.md"
    }
  },
  "backend": {
    "imageid": "ubuntu"
  }
}
